{
    "mesas_totales": 197,
    "mesas_escrutadas": 110,
    "porc_mesas_escrutadas": 5584,
    "electores": 57076,
    "votantes": 22341,
    "participacion_sobre_censo": 3914,
    "participacion_sobre_escrutado": 7035,
    "electores_escrutados": 31758,
    "porc_electores_escrutados": 5564,
    "votos_validos": 22341,
    "porc_votos_validos": 3914,
    "votos_positivos": 20942,
    "porc_votos_positivos": 9374,
    "votos_en_blanco": 1297,
    "porc_votos_en_blanco": 581,
    "votos_nulos": 94,
    "porc_votos_nulos": 42,
    "votos_recurridos_impugnados": 8,
    "porc_votos_recurridos_impugnados": 3,
    "cargos_a_elegir": 0,
    "dia": 26,
    "hora": 6,
    "minuto": 55
}