{
    "mesas_totales": 212,
    "mesas_escrutadas": 212,
    "porc_mesas_escrutadas": 10000,
    "electores": 72623,
    "votantes": 54163,
    "participacion_sobre_censo": 7458,
    "participacion_sobre_escrutado": 7458,
    "electores_escrutados": 72623,
    "porc_electores_escrutados": 10000,
    "votos_validos": 54163,
    "porc_votos_validos": 7458,
    "votos_positivos": 51762,
    "porc_votos_positivos": 9557,
    "votos_en_blanco": 2136,
    "porc_votos_en_blanco": 394,
    "votos_nulos": 244,
    "porc_votos_nulos": 45,
    "votos_recurridos_impugnados": 21,
    "porc_votos_recurridos_impugnados": 4,
    "cargos_a_elegir": 0,
    "dia": 26,
    "hora": 3,
    "minuto": 5
}