{
    "mesas_totales": 147,
    "mesas_escrutadas": 145,
    "porc_mesas_escrutadas": 9864,
    "electores": 50002,
    "votantes": 39966,
    "participacion_sobre_censo": 7993,
    "participacion_sobre_escrutado": 8105,
    "electores_escrutados": 49311,
    "porc_electores_escrutados": 9862,
    "votos_validos": 39966,
    "porc_votos_validos": 7993,
    "votos_positivos": 30091,
    "porc_votos_positivos": 7529,
    "votos_en_blanco": 9506,
    "porc_votos_en_blanco": 2379,
    "votos_nulos": 313,
    "porc_votos_nulos": 78,
    "votos_recurridos_impugnados": 56,
    "porc_votos_recurridos_impugnados": 14,
    "cargos_a_elegir": 0,
    "dia": 26,
    "hora": 7,
    "minuto": 10
}