[
    {
        "dia": 26,
        "hora": 3,
        "minuto": 25,
        "codigo_agrupacion": 501,
        "votos_agrupacion": 178,
        "porc_final_agrupacion": 5086,
        "cargos_electos": 0
    },
    {
        "dia": 26,
        "hora": 3,
        "minuto": 25,
        "codigo_agrupacion": 179,
        "votos_agrupacion": 172,
        "porc_final_agrupacion": 4914,
        "cargos_electos": 0
    },
    {
        "dia": 26,
        "hora": 3,
        "minuto": 25,
        "codigo_agrupacion": 68,
        "votos_agrupacion": 0,
        "porc_final_agrupacion": 0,
        "cargos_electos": 0
    },
    {
        "dia": 26,
        "hora": 3,
        "minuto": 25,
        "codigo_agrupacion": 72,
        "votos_agrupacion": 0,
        "porc_final_agrupacion": 0,
        "cargos_electos": 0
    },
    {
        "dia": 26,
        "hora": 3,
        "minuto": 25,
        "codigo_agrupacion": 103,
        "votos_agrupacion": 0,
        "porc_final_agrupacion": 0,
        "cargos_electos": 0
    },
    {
        "dia": 26,
        "hora": 3,
        "minuto": 25,
        "codigo_agrupacion": 251,
        "votos_agrupacion": 0,
        "porc_final_agrupacion": 0,
        "cargos_electos": 0
    },
    {
        "dia": 26,
        "hora": 3,
        "minuto": 25,
        "codigo_agrupacion": 406,
        "votos_agrupacion": 0,
        "porc_final_agrupacion": 0,
        "cargos_electos": 0
    }
]