{
    "mesas_totales": 14,
    "mesas_escrutadas": 12,
    "porc_mesas_escrutadas": 8571,
    "electores": 3587,
    "votantes": 2162,
    "participacion_sobre_censo": 6027,
    "participacion_sobre_escrutado": 7292,
    "electores_escrutados": 2965,
    "porc_electores_escrutados": 8266,
    "votos_validos": 2162,
    "porc_votos_validos": 6027,
    "votos_positivos": 1813,
    "porc_votos_positivos": 8386,
    "votos_en_blanco": 345,
    "porc_votos_en_blanco": 1596,
    "votos_nulos": 3,
    "porc_votos_nulos": 14,
    "votos_recurridos_impugnados": 1,
    "porc_votos_recurridos_impugnados": 4,
    "cargos_a_elegir": 0,
    "dia": 26,
    "hora": 0,
    "minuto": 25
}