{
    "mesas_totales": 11,
    "mesas_escrutadas": 11,
    "porc_mesas_escrutadas": 10000,
    "electores": 2962,
    "votantes": 1802,
    "participacion_sobre_censo": 6084,
    "participacion_sobre_escrutado": 6084,
    "electores_escrutados": 2962,
    "porc_electores_escrutados": 10000,
    "votos_validos": 1802,
    "porc_votos_validos": 6084,
    "votos_positivos": 1755,
    "porc_votos_positivos": 9739,
    "votos_en_blanco": 38,
    "porc_votos_en_blanco": 211,
    "votos_nulos": 7,
    "porc_votos_nulos": 39,
    "votos_recurridos_impugnados": 2,
    "porc_votos_recurridos_impugnados": 11,
    "cargos_a_elegir": 0,
    "dia": 26,
    "hora": 3,
    "minuto": 30
}