{
    "mesas_totales": 37,
    "mesas_escrutadas": 36,
    "porc_mesas_escrutadas": 9730,
    "electores": 9589,
    "votantes": 7750,
    "participacion_sobre_censo": 8082,
    "participacion_sobre_escrutado": 8384,
    "electores_escrutados": 9244,
    "porc_electores_escrutados": 9640,
    "votos_validos": 7750,
    "porc_votos_validos": 8082,
    "votos_positivos": 7255,
    "porc_votos_positivos": 9361,
    "votos_en_blanco": 430,
    "porc_votos_en_blanco": 555,
    "votos_nulos": 50,
    "porc_votos_nulos": 65,
    "votos_recurridos_impugnados": 15,
    "porc_votos_recurridos_impugnados": 19,
    "cargos_a_elegir": 0,
    "dia": 26,
    "hora": 3,
    "minuto": 45
}