[
    {
        "dia": 25,
        "hora": 23,
        "minuto": 15,
        "codigo_agrupacion": 135,
        "votos_agrupacion": 11629,
        "porc_final_agrupacion": 4334,
        "cargos_electos": 0
    },
    {
        "dia": 25,
        "hora": 23,
        "minuto": 15,
        "codigo_agrupacion": 131,
        "votos_agrupacion": 7883,
        "porc_final_agrupacion": 2938,
        "cargos_electos": 0
    },
    {
        "dia": 25,
        "hora": 23,
        "minuto": 15,
        "codigo_agrupacion": 138,
        "votos_agrupacion": 5358,
        "porc_final_agrupacion": 1997,
        "cargos_electos": 0
    },
    {
        "dia": 25,
        "hora": 23,
        "minuto": 15,
        "codigo_agrupacion": 132,
        "votos_agrupacion": 1080,
        "porc_final_agrupacion": 402,
        "cargos_electos": 0
    },
    {
        "dia": 25,
        "hora": 23,
        "minuto": 15,
        "codigo_agrupacion": 137,
        "votos_agrupacion": 510,
        "porc_final_agrupacion": 190,
        "cargos_electos": 0
    },
    {
        "dia": 25,
        "hora": 23,
        "minuto": 15,
        "codigo_agrupacion": 133,
        "votos_agrupacion": 373,
        "porc_final_agrupacion": 139,
        "cargos_electos": 0
    }
]