[
    {
        "dia": 26,
        "hora": 3,
        "minuto": 10,
        "codigo_agrupacion": 131,
        "votos_agrupacion": 4679,
        "porc_final_agrupacion": 5150,
        "cargos_electos": 0
    },
    {
        "dia": 26,
        "hora": 3,
        "minuto": 10,
        "codigo_agrupacion": 135,
        "votos_agrupacion": 2102,
        "porc_final_agrupacion": 2313,
        "cargos_electos": 0
    },
    {
        "dia": 26,
        "hora": 3,
        "minuto": 10,
        "codigo_agrupacion": 138,
        "votos_agrupacion": 2013,
        "porc_final_agrupacion": 2215,
        "cargos_electos": 0
    },
    {
        "dia": 26,
        "hora": 3,
        "minuto": 10,
        "codigo_agrupacion": 137,
        "votos_agrupacion": 120,
        "porc_final_agrupacion": 132,
        "cargos_electos": 0
    },
    {
        "dia": 26,
        "hora": 3,
        "minuto": 10,
        "codigo_agrupacion": 133,
        "votos_agrupacion": 117,
        "porc_final_agrupacion": 129,
        "cargos_electos": 0
    },
    {
        "dia": 26,
        "hora": 3,
        "minuto": 10,
        "codigo_agrupacion": 132,
        "votos_agrupacion": 55,
        "porc_final_agrupacion": 61,
        "cargos_electos": 0
    }
]