{
    "mesas_totales": 48,
    "mesas_escrutadas": 44,
    "porc_mesas_escrutadas": 9167,
    "electores": 15497,
    "votantes": 11803,
    "participacion_sobre_censo": 7616,
    "participacion_sobre_escrutado": 8315,
    "electores_escrutados": 14195,
    "porc_electores_escrutados": 9160,
    "votos_validos": 11803,
    "porc_votos_validos": 7616,
    "votos_positivos": 10518,
    "porc_votos_positivos": 8911,
    "votos_en_blanco": 1247,
    "porc_votos_en_blanco": 1057,
    "votos_nulos": 35,
    "porc_votos_nulos": 30,
    "votos_recurridos_impugnados": 3,
    "porc_votos_recurridos_impugnados": 2,
    "cargos_a_elegir": 0,
    "dia": 26,
    "hora": 4,
    "minuto": 0
}