[
    {
        "dia": 26,
        "hora": 0,
        "minuto": 55,
        "codigo_agrupacion": 131,
        "votos_agrupacion": 1826,
        "porc_final_agrupacion": 5364,
        "cargos_electos": 0
    },
    {
        "dia": 26,
        "hora": 0,
        "minuto": 55,
        "codigo_agrupacion": 135,
        "votos_agrupacion": 1149,
        "porc_final_agrupacion": 3375,
        "cargos_electos": 0
    },
    {
        "dia": 26,
        "hora": 0,
        "minuto": 55,
        "codigo_agrupacion": 138,
        "votos_agrupacion": 280,
        "porc_final_agrupacion": 823,
        "cargos_electos": 0
    },
    {
        "dia": 26,
        "hora": 0,
        "minuto": 55,
        "codigo_agrupacion": 133,
        "votos_agrupacion": 77,
        "porc_final_agrupacion": 226,
        "cargos_electos": 0
    },
    {
        "dia": 26,
        "hora": 0,
        "minuto": 55,
        "codigo_agrupacion": 137,
        "votos_agrupacion": 47,
        "porc_final_agrupacion": 138,
        "cargos_electos": 0
    },
    {
        "dia": 26,
        "hora": 0,
        "minuto": 55,
        "codigo_agrupacion": 132,
        "votos_agrupacion": 25,
        "porc_final_agrupacion": 73,
        "cargos_electos": 0
    }
]