{
    "mesas_totales": 40,
    "mesas_escrutadas": 40,
    "porc_mesas_escrutadas": 10000,
    "electores": 13158,
    "votantes": 10091,
    "participacion_sobre_censo": 7669,
    "participacion_sobre_escrutado": 7669,
    "electores_escrutados": 13158,
    "porc_electores_escrutados": 10000,
    "votos_validos": 10091,
    "porc_votos_validos": 7669,
    "votos_positivos": 7379,
    "porc_votos_positivos": 7312,
    "votos_en_blanco": 2491,
    "porc_votos_en_blanco": 2469,
    "votos_nulos": 112,
    "porc_votos_nulos": 111,
    "votos_recurridos_impugnados": 109,
    "porc_votos_recurridos_impugnados": 108,
    "cargos_a_elegir": 0,
    "dia": 26,
    "hora": 4,
    "minuto": 20
}