{
    "mesas_totales": 29,
    "mesas_escrutadas": 25,
    "porc_mesas_escrutadas": 8621,
    "electores": 8408,
    "votantes": 6006,
    "participacion_sobre_censo": 7143,
    "participacion_sobre_escrutado": 8298,
    "electores_escrutados": 7238,
    "porc_electores_escrutados": 8608,
    "votos_validos": 6006,
    "porc_votos_validos": 7143,
    "votos_positivos": 5429,
    "porc_votos_positivos": 9039,
    "votos_en_blanco": 558,
    "porc_votos_en_blanco": 929,
    "votos_nulos": 14,
    "porc_votos_nulos": 23,
    "votos_recurridos_impugnados": 5,
    "porc_votos_recurridos_impugnados": 9,
    "cargos_a_elegir": 1,
    "dia": 26,
    "hora": 9,
    "minuto": 40
}