{
    "mesas_totales": 24,
    "mesas_escrutadas": 23,
    "porc_mesas_escrutadas": 9583,
    "electores": 7712,
    "votantes": 6095,
    "participacion_sobre_censo": 7903,
    "participacion_sobre_escrutado": 8278,
    "electores_escrutados": 7363,
    "porc_electores_escrutados": 9547,
    "votos_validos": 6095,
    "porc_votos_validos": 7903,
    "votos_positivos": 5879,
    "porc_votos_positivos": 9646,
    "votos_en_blanco": 191,
    "porc_votos_en_blanco": 313,
    "votos_nulos": 21,
    "porc_votos_nulos": 34,
    "votos_recurridos_impugnados": 4,
    "porc_votos_recurridos_impugnados": 7,
    "cargos_a_elegir": 1,
    "dia": 26,
    "hora": 3,
    "minuto": 5
}