{
    "mesas_totales": 22,
    "mesas_escrutadas": 22,
    "porc_mesas_escrutadas": 10000,
    "electores": 6412,
    "votantes": 4476,
    "participacion_sobre_censo": 6981,
    "participacion_sobre_escrutado": 6981,
    "electores_escrutados": 6412,
    "porc_electores_escrutados": 10000,
    "votos_validos": 4476,
    "porc_votos_validos": 6981,
    "votos_positivos": 4186,
    "porc_votos_positivos": 9352,
    "votos_en_blanco": 274,
    "porc_votos_en_blanco": 612,
    "votos_nulos": 16,
    "porc_votos_nulos": 36,
    "votos_recurridos_impugnados": 0,
    "porc_votos_recurridos_impugnados": 0,
    "cargos_a_elegir": 0,
    "dia": 26,
    "hora": 1,
    "minuto": 55
}