{
    "mesas_totales": 195,
    "mesas_escrutadas": 192,
    "porc_mesas_escrutadas": 9846,
    "electores": 66767,
    "votantes": 55196,
    "participacion_sobre_censo": 8267,
    "participacion_sobre_escrutado": 8397,
    "electores_escrutados": 65735,
    "porc_electores_escrutados": 9845,
    "votos_validos": 55196,
    "porc_votos_validos": 8267,
    "votos_positivos": 47590,
    "porc_votos_positivos": 8622,
    "votos_en_blanco": 7199,
    "porc_votos_en_blanco": 1304,
    "votos_nulos": 369,
    "porc_votos_nulos": 67,
    "votos_recurridos_impugnados": 38,
    "porc_votos_recurridos_impugnados": 7,
    "cargos_a_elegir": 0,
    "dia": 25,
    "hora": 23,
    "minuto": 55
}