[
    {
        "dia": 26,
        "hora": 0,
        "minuto": 20,
        "codigo_agrupacion": 135,
        "votos_agrupacion": 34458,
        "porc_final_agrupacion": 5203,
        "cargos_electos": 0
    },
    {
        "dia": 26,
        "hora": 0,
        "minuto": 20,
        "codigo_agrupacion": 138,
        "votos_agrupacion": 14029,
        "porc_final_agrupacion": 2118,
        "cargos_electos": 0
    },
    {
        "dia": 26,
        "hora": 0,
        "minuto": 20,
        "codigo_agrupacion": 131,
        "votos_agrupacion": 11331,
        "porc_final_agrupacion": 1711,
        "cargos_electos": 0
    },
    {
        "dia": 26,
        "hora": 0,
        "minuto": 20,
        "codigo_agrupacion": 137,
        "votos_agrupacion": 2987,
        "porc_final_agrupacion": 451,
        "cargos_electos": 0
    },
    {
        "dia": 26,
        "hora": 0,
        "minuto": 20,
        "codigo_agrupacion": 132,
        "votos_agrupacion": 1854,
        "porc_final_agrupacion": 280,
        "cargos_electos": 0
    },
    {
        "dia": 26,
        "hora": 0,
        "minuto": 20,
        "codigo_agrupacion": 133,
        "votos_agrupacion": 1572,
        "porc_final_agrupacion": 237,
        "cargos_electos": 0
    }
]