{
    "mesas_totales": 728,
    "mesas_escrutadas": 726,
    "porc_mesas_escrutadas": 9973,
    "electores": 251382,
    "votantes": 206963,
    "participacion_sobre_censo": 8233,
    "participacion_sobre_escrutado": 8255,
    "electores_escrutados": 250705,
    "porc_electores_escrutados": 9973,
    "votos_validos": 206963,
    "porc_votos_validos": 8233,
    "votos_positivos": 189698,
    "porc_votos_positivos": 9166,
    "votos_en_blanco": 14329,
    "porc_votos_en_blanco": 692,
    "votos_nulos": 2884,
    "porc_votos_nulos": 139,
    "votos_recurridos_impugnados": 52,
    "porc_votos_recurridos_impugnados": 3,
    "cargos_a_elegir": 0,
    "dia": 26,
    "hora": 9,
    "minuto": 25
}