[
    {
        "dia": 25,
        "hora": 23,
        "minuto": 30,
        "codigo_agrupacion": 533,
        "votos_agrupacion": 6849,
        "porc_final_agrupacion": 7167,
        "cargos_electos": 0
    },
    {
        "dia": 25,
        "hora": 23,
        "minuto": 30,
        "codigo_agrupacion": 135,
        "votos_agrupacion": 1634,
        "porc_final_agrupacion": 1710,
        "cargos_electos": 0
    },
    {
        "dia": 25,
        "hora": 23,
        "minuto": 30,
        "codigo_agrupacion": 138,
        "votos_agrupacion": 1073,
        "porc_final_agrupacion": 1123,
        "cargos_electos": 0
    }
]