[
    {
        "dia": 26,
        "hora": 1,
        "minuto": 45,
        "codigo_agrupacion": 501,
        "votos_agrupacion": 25223,
        "porc_final_agrupacion": 5921,
        "cargos_electos": 1
    },
    {
        "dia": 26,
        "hora": 1,
        "minuto": 45,
        "codigo_agrupacion": 821,
        "votos_agrupacion": 8519,
        "porc_final_agrupacion": 2000,
        "cargos_electos": 0
    },
    {
        "dia": 26,
        "hora": 1,
        "minuto": 45,
        "codigo_agrupacion": 518,
        "votos_agrupacion": 8214,
        "porc_final_agrupacion": 1928,
        "cargos_electos": 0
    },
    {
        "dia": 26,
        "hora": 1,
        "minuto": 45,
        "codigo_agrupacion": 153,
        "votos_agrupacion": 641,
        "porc_final_agrupacion": 150,
        "cargos_electos": 0
    }
]