{
    "mesas_totales": 1241,
    "mesas_escrutadas": 1185,
    "porc_mesas_escrutadas": 9549,
    "electores": 416710,
    "votantes": 308396,
    "participacion_sobre_censo": 7401,
    "participacion_sobre_escrutado": 7753,
    "electores_escrutados": 397763,
    "porc_electores_escrutados": 9545,
    "votos_validos": 308396,
    "porc_votos_validos": 7401,
    "votos_positivos": 263843,
    "porc_votos_positivos": 8555,
    "votos_en_blanco": 39258,
    "porc_votos_en_blanco": 1273,
    "votos_nulos": 4604,
    "porc_votos_nulos": 149,
    "votos_recurridos_impugnados": 691,
    "porc_votos_recurridos_impugnados": 23,
    "cargos_a_elegir": 0,
    "dia": 26,
    "hora": 9,
    "minuto": 30
}