{
    "mesas_totales": 37,
    "mesas_escrutadas": 35,
    "porc_mesas_escrutadas": 9459,
    "electores": 12551,
    "votantes": 9476,
    "participacion_sobre_censo": 7550,
    "participacion_sobre_escrutado": 7987,
    "electores_escrutados": 11865,
    "porc_electores_escrutados": 9453,
    "votos_validos": 9476,
    "porc_votos_validos": 7550,
    "votos_positivos": 8895,
    "porc_votos_positivos": 9387,
    "votos_en_blanco": 533,
    "porc_votos_en_blanco": 562,
    "votos_nulos": 31,
    "porc_votos_nulos": 33,
    "votos_recurridos_impugnados": 17,
    "porc_votos_recurridos_impugnados": 18,
    "cargos_a_elegir": 1,
    "dia": 26,
    "hora": 1,
    "minuto": 35
}