{
    "mesas_totales": 758,
    "mesas_escrutadas": 736,
    "porc_mesas_escrutadas": 9710,
    "electores": 263066,
    "votantes": 204474,
    "participacion_sobre_censo": 7773,
    "participacion_sobre_escrutado": 8004,
    "electores_escrutados": 255470,
    "porc_electores_escrutados": 9711,
    "votos_validos": 204474,
    "porc_votos_validos": 7773,
    "votos_positivos": 167184,
    "porc_votos_positivos": 8176,
    "votos_en_blanco": 35488,
    "porc_votos_en_blanco": 1736,
    "votos_nulos": 1697,
    "porc_votos_nulos": 83,
    "votos_recurridos_impugnados": 105,
    "porc_votos_recurridos_impugnados": 5,
    "cargos_a_elegir": 0,
    "dia": 26,
    "hora": 8,
    "minuto": 20
}