{
    "mesas_totales": 947,
    "mesas_escrutadas": 904,
    "porc_mesas_escrutadas": 9546,
    "electores": 333566,
    "votantes": 257474,
    "participacion_sobre_censo": 7719,
    "participacion_sobre_escrutado": 8079,
    "electores_escrutados": 318677,
    "porc_electores_escrutados": 9554,
    "votos_validos": 257474,
    "porc_votos_validos": 7719,
    "votos_positivos": 227640,
    "porc_votos_positivos": 8841,
    "votos_en_blanco": 28029,
    "porc_votos_en_blanco": 1089,
    "votos_nulos": 1510,
    "porc_votos_nulos": 59,
    "votos_recurridos_impugnados": 295,
    "porc_votos_recurridos_impugnados": 11,
    "cargos_a_elegir": 1,
    "dia": 26,
    "hora": 9,
    "minuto": 0
}