{
    "mesas_totales": 74,
    "mesas_escrutadas": 74,
    "porc_mesas_escrutadas": 10000,
    "electores": 25256,
    "votantes": 20069,
    "participacion_sobre_censo": 7946,
    "participacion_sobre_escrutado": 7946,
    "electores_escrutados": 25256,
    "porc_electores_escrutados": 10000,
    "votos_validos": 20069,
    "porc_votos_validos": 7946,
    "votos_positivos": 17459,
    "porc_votos_positivos": 8699,
    "votos_en_blanco": 2325,
    "porc_votos_en_blanco": 1159,
    "votos_nulos": 119,
    "porc_votos_nulos": 59,
    "votos_recurridos_impugnados": 166,
    "porc_votos_recurridos_impugnados": 83,
    "cargos_a_elegir": 0,
    "dia": 26,
    "hora": 7,
    "minuto": 20
}