{
    "mesas_totales": 24,
    "mesas_escrutadas": 23,
    "porc_mesas_escrutadas": 9583,
    "electores": 7446,
    "votantes": 6008,
    "participacion_sobre_censo": 8069,
    "participacion_sobre_escrutado": 8449,
    "electores_escrutados": 7111,
    "porc_electores_escrutados": 9550,
    "votos_validos": 6008,
    "porc_votos_validos": 8069,
    "votos_positivos": 5675,
    "porc_votos_positivos": 9446,
    "votos_en_blanco": 319,
    "porc_votos_en_blanco": 531,
    "votos_nulos": 14,
    "porc_votos_nulos": 23,
    "votos_recurridos_impugnados": 0,
    "porc_votos_recurridos_impugnados": 0,
    "cargos_a_elegir": 0,
    "dia": 26,
    "hora": 3,
    "minuto": 5
}