{
    "mesas_totales": 535,
    "mesas_escrutadas": 519,
    "porc_mesas_escrutadas": 9701,
    "electores": 181362,
    "votantes": 140684,
    "participacion_sobre_censo": 7757,
    "participacion_sobre_escrutado": 7993,
    "electores_escrutados": 176019,
    "porc_electores_escrutados": 9705,
    "votos_validos": 140684,
    "porc_votos_validos": 7757,
    "votos_positivos": 134853,
    "porc_votos_positivos": 9586,
    "votos_en_blanco": 4343,
    "porc_votos_en_blanco": 309,
    "votos_nulos": 1317,
    "porc_votos_nulos": 94,
    "votos_recurridos_impugnados": 171,
    "porc_votos_recurridos_impugnados": 11,
    "cargos_a_elegir": 0,
    "dia": 26,
    "hora": 5,
    "minuto": 35
}