{
    "mesas_totales": 30,
    "mesas_escrutadas": 30,
    "porc_mesas_escrutadas": 10000,
    "electores": 8614,
    "votantes": 6368,
    "participacion_sobre_censo": 7393,
    "participacion_sobre_escrutado": 7393,
    "electores_escrutados": 8614,
    "porc_electores_escrutados": 10000,
    "votos_validos": 6368,
    "porc_votos_validos": 7393,
    "votos_positivos": 6075,
    "porc_votos_positivos": 9540,
    "votos_en_blanco": 232,
    "porc_votos_en_blanco": 364,
    "votos_nulos": 60,
    "porc_votos_nulos": 94,
    "votos_recurridos_impugnados": 1,
    "porc_votos_recurridos_impugnados": 2,
    "cargos_a_elegir": 0,
    "dia": 26,
    "hora": 3,
    "minuto": 10
}