[
    {
        "dia": 26,
        "hora": 7,
        "minuto": 10,
        "codigo_agrupacion": 145,
        "votos_agrupacion": 90067,
        "porc_final_agrupacion": 4223,
        "cargos_electos": 0
    },
    {
        "dia": 26,
        "hora": 7,
        "minuto": 10,
        "codigo_agrupacion": 131,
        "votos_agrupacion": 65960,
        "porc_final_agrupacion": 3092,
        "cargos_electos": 0
    },
    {
        "dia": 26,
        "hora": 7,
        "minuto": 10,
        "codigo_agrupacion": 138,
        "votos_agrupacion": 42869,
        "porc_final_agrupacion": 2010,
        "cargos_electos": 0
    },
    {
        "dia": 26,
        "hora": 7,
        "minuto": 10,
        "codigo_agrupacion": 137,
        "votos_agrupacion": 8933,
        "porc_final_agrupacion": 419,
        "cargos_electos": 0
    },
    {
        "dia": 26,
        "hora": 7,
        "minuto": 10,
        "codigo_agrupacion": 132,
        "votos_agrupacion": 5472,
        "porc_final_agrupacion": 257,
        "cargos_electos": 0
    }
]