{
    "mesas_totales": 92,
    "mesas_escrutadas": 92,
    "porc_mesas_escrutadas": 10000,
    "electores": 31184,
    "votantes": 24890,
    "participacion_sobre_censo": 7982,
    "participacion_sobre_escrutado": 7982,
    "electores_escrutados": 31184,
    "porc_electores_escrutados": 10000,
    "votos_validos": 24890,
    "porc_votos_validos": 7982,
    "votos_positivos": 23700,
    "porc_votos_positivos": 9522,
    "votos_en_blanco": 1110,
    "porc_votos_en_blanco": 446,
    "votos_nulos": 77,
    "porc_votos_nulos": 31,
    "votos_recurridos_impugnados": 3,
    "porc_votos_recurridos_impugnados": 1,
    "cargos_a_elegir": 0,
    "dia": 26,
    "hora": 3,
    "minuto": 10
}