{
    "mesas_totales": 17,
    "mesas_escrutadas": 15,
    "porc_mesas_escrutadas": 8824,
    "electores": 3973,
    "votantes": 2684,
    "participacion_sobre_censo": 6756,
    "participacion_sobre_escrutado": 7366,
    "electores_escrutados": 3644,
    "porc_electores_escrutados": 9172,
    "votos_validos": 2684,
    "porc_votos_validos": 6756,
    "votos_positivos": 2510,
    "porc_votos_positivos": 9352,
    "votos_en_blanco": 161,
    "porc_votos_en_blanco": 600,
    "votos_nulos": 10,
    "porc_votos_nulos": 37,
    "votos_recurridos_impugnados": 3,
    "porc_votos_recurridos_impugnados": 11,
    "cargos_a_elegir": 0,
    "dia": 26,
    "hora": 5,
    "minuto": 30
}