{
    "mesas_totales": 40,
    "mesas_escrutadas": 17,
    "porc_mesas_escrutadas": 4250,
    "electores": 11247,
    "votantes": 3949,
    "participacion_sobre_censo": 3511,
    "participacion_sobre_escrutado": 7498,
    "electores_escrutados": 5267,
    "porc_electores_escrutados": 4683,
    "votos_validos": 3949,
    "porc_votos_validos": 3511,
    "votos_positivos": 3893,
    "porc_votos_positivos": 9858,
    "votos_en_blanco": 44,
    "porc_votos_en_blanco": 111,
    "votos_nulos": 10,
    "porc_votos_nulos": 25,
    "votos_recurridos_impugnados": 2,
    "porc_votos_recurridos_impugnados": 6,
    "cargos_a_elegir": 0,
    "dia": 26,
    "hora": 6,
    "minuto": 50
}