{
    "mesas_totales": 30,
    "mesas_escrutadas": 29,
    "porc_mesas_escrutadas": 9667,
    "electores": 9135,
    "votantes": 7546,
    "participacion_sobre_censo": 8261,
    "participacion_sobre_escrutado": 8274,
    "electores_escrutados": 9120,
    "porc_electores_escrutados": 9984,
    "votos_validos": 7546,
    "porc_votos_validos": 8261,
    "votos_positivos": 6816,
    "porc_votos_positivos": 9033,
    "votos_en_blanco": 704,
    "porc_votos_en_blanco": 933,
    "votos_nulos": 20,
    "porc_votos_nulos": 27,
    "votos_recurridos_impugnados": 6,
    "porc_votos_recurridos_impugnados": 7,
    "cargos_a_elegir": 0,
    "dia": 26,
    "hora": 2,
    "minuto": 15
}