{
    "mesas_totales": 16,
    "mesas_escrutadas": 16,
    "porc_mesas_escrutadas": 10000,
    "electores": 5197,
    "votantes": 3571,
    "participacion_sobre_censo": 6871,
    "participacion_sobre_escrutado": 6871,
    "electores_escrutados": 5197,
    "porc_electores_escrutados": 10000,
    "votos_validos": 3571,
    "porc_votos_validos": 6871,
    "votos_positivos": 3267,
    "porc_votos_positivos": 9149,
    "votos_en_blanco": 234,
    "porc_votos_en_blanco": 655,
    "votos_nulos": 18,
    "porc_votos_nulos": 50,
    "votos_recurridos_impugnados": 52,
    "porc_votos_recurridos_impugnados": 146,
    "cargos_a_elegir": 0,
    "dia": 26,
    "hora": 5,
    "minuto": 50
}