[
    {
        "dia": 26,
        "hora": 9,
        "minuto": 50,
        "codigo_agrupacion": 501,
        "votos_agrupacion": 213244,
        "porc_final_agrupacion": 5359,
        "cargos_electos": 0
    },
    {
        "dia": 26,
        "hora": 9,
        "minuto": 50,
        "codigo_agrupacion": 518,
        "votos_agrupacion": 121838,
        "porc_final_agrupacion": 3062,
        "cargos_electos": 0
    },
    {
        "dia": 26,
        "hora": 9,
        "minuto": 50,
        "codigo_agrupacion": 821,
        "votos_agrupacion": 48560,
        "porc_final_agrupacion": 1220,
        "cargos_electos": 0
    },
    {
        "dia": 26,
        "hora": 9,
        "minuto": 50,
        "codigo_agrupacion": 526,
        "votos_agrupacion": 6760,
        "porc_final_agrupacion": 170,
        "cargos_electos": 0
    },
    {
        "dia": 26,
        "hora": 9,
        "minuto": 50,
        "codigo_agrupacion": 153,
        "votos_agrupacion": 5596,
        "porc_final_agrupacion": 141,
        "cargos_electos": 0
    },
    {
        "dia": 26,
        "hora": 9,
        "minuto": 50,
        "codigo_agrupacion": 68,
        "votos_agrupacion": 1905,
        "porc_final_agrupacion": 48,
        "cargos_electos": 0
    }
]