[
    {
        "dia": 26,
        "hora": 9,
        "minuto": 30,
        "codigo_agrupacion": 501,
        "votos_agrupacion": 101210,
        "porc_final_agrupacion": 4177,
        "cargos_electos": 12
    },
    {
        "dia": 26,
        "hora": 9,
        "minuto": 30,
        "codigo_agrupacion": 531,
        "votos_agrupacion": 91339,
        "porc_final_agrupacion": 3769,
        "cargos_electos": 10
    },
    {
        "dia": 26,
        "hora": 9,
        "minuto": 30,
        "codigo_agrupacion": 530,
        "votos_agrupacion": 41547,
        "porc_final_agrupacion": 1714,
        "cargos_electos": 5
    },
    {
        "dia": 26,
        "hora": 9,
        "minuto": 30,
        "codigo_agrupacion": 152,
        "votos_agrupacion": 8232,
        "porc_final_agrupacion": 340,
        "cargos_electos": 0
    }
]