{
    "mesas_totales": 296,
    "mesas_escrutadas": 296,
    "porc_mesas_escrutadas": 10000,
    "electores": 99182,
    "votantes": 77082,
    "participacion_sobre_censo": 7772,
    "participacion_sobre_escrutado": 7772,
    "electores_escrutados": 99182,
    "porc_electores_escrutados": 10000,
    "votos_validos": 77082,
    "porc_votos_validos": 7772,
    "votos_positivos": 73507,
    "porc_votos_positivos": 9536,
    "votos_en_blanco": 2826,
    "porc_votos_en_blanco": 367,
    "votos_nulos": 706,
    "porc_votos_nulos": 92,
    "votos_recurridos_impugnados": 43,
    "porc_votos_recurridos_impugnados": 5,
    "cargos_a_elegir": 0,
    "dia": 25,
    "hora": 22,
    "minuto": 55
}