{
    "mesas_totales": 2403,
    "mesas_escrutadas": 2388,
    "porc_mesas_escrutadas": 9938,
    "electores": 810712,
    "votantes": 594172,
    "participacion_sobre_censo": 7329,
    "participacion_sobre_escrutado": 7376,
    "electores_escrutados": 805577,
    "porc_electores_escrutados": 9937,
    "votos_validos": 594172,
    "porc_votos_validos": 7329,
    "votos_positivos": 555833,
    "porc_votos_positivos": 9355,
    "votos_en_blanco": 35140,
    "porc_votos_en_blanco": 591,
    "votos_nulos": 2978,
    "porc_votos_nulos": 50,
    "votos_recurridos_impugnados": 221,
    "porc_votos_recurridos_impugnados": 4,
    "cargos_a_elegir": 4,
    "dia": 26,
    "hora": 8,
    "minuto": 15
}