{
    "mesas_totales": 97,
    "mesas_escrutadas": 95,
    "porc_mesas_escrutadas": 9794,
    "electores": 30809,
    "votantes": 23263,
    "participacion_sobre_censo": 7551,
    "participacion_sobre_escrutado": 7648,
    "electores_escrutados": 30417,
    "porc_electores_escrutados": 9873,
    "votos_validos": 23263,
    "porc_votos_validos": 7551,
    "votos_positivos": 21845,
    "porc_votos_positivos": 9390,
    "votos_en_blanco": 1316,
    "porc_votos_en_blanco": 566,
    "votos_nulos": 89,
    "porc_votos_nulos": 38,
    "votos_recurridos_impugnados": 13,
    "porc_votos_recurridos_impugnados": 6,
    "cargos_a_elegir": 0,
    "dia": 26,
    "hora": 3,
    "minuto": 0
}