[
    {
        "dia": 26,
        "hora": 0,
        "minuto": 15,
        "codigo_agrupacion": 135,
        "votos_agrupacion": 22177,
        "porc_final_agrupacion": 4019,
        "cargos_electos": 0
    },
    {
        "dia": 26,
        "hora": 0,
        "minuto": 15,
        "codigo_agrupacion": 131,
        "votos_agrupacion": 15813,
        "porc_final_agrupacion": 2866,
        "cargos_electos": 0
    },
    {
        "dia": 26,
        "hora": 0,
        "minuto": 15,
        "codigo_agrupacion": 138,
        "votos_agrupacion": 12963,
        "porc_final_agrupacion": 2349,
        "cargos_electos": 0
    },
    {
        "dia": 26,
        "hora": 0,
        "minuto": 15,
        "codigo_agrupacion": 132,
        "votos_agrupacion": 1729,
        "porc_final_agrupacion": 313,
        "cargos_electos": 0
    },
    {
        "dia": 26,
        "hora": 0,
        "minuto": 15,
        "codigo_agrupacion": 137,
        "votos_agrupacion": 1455,
        "porc_final_agrupacion": 264,
        "cargos_electos": 0
    },
    {
        "dia": 26,
        "hora": 0,
        "minuto": 15,
        "codigo_agrupacion": 133,
        "votos_agrupacion": 1044,
        "porc_final_agrupacion": 189,
        "cargos_electos": 0
    }
]