{
    "mesas_totales": 120,
    "mesas_escrutadas": 119,
    "porc_mesas_escrutadas": 9917,
    "electores": 40661,
    "votantes": 33228,
    "participacion_sobre_censo": 8172,
    "participacion_sobre_escrutado": 8244,
    "electores_escrutados": 40308,
    "porc_electores_escrutados": 9913,
    "votos_validos": 33228,
    "porc_votos_validos": 8172,
    "votos_positivos": 29019,
    "porc_votos_positivos": 8733,
    "votos_en_blanco": 4073,
    "porc_votos_en_blanco": 1226,
    "votos_nulos": 128,
    "porc_votos_nulos": 39,
    "votos_recurridos_impugnados": 8,
    "porc_votos_recurridos_impugnados": 2,
    "cargos_a_elegir": 0,
    "dia": 26,
    "hora": 7,
    "minuto": 30
}