{
    "mesas_totales": 82,
    "mesas_escrutadas": 82,
    "porc_mesas_escrutadas": 10000,
    "electores": 26579,
    "votantes": 19123,
    "participacion_sobre_censo": 7195,
    "participacion_sobre_escrutado": 7195,
    "electores_escrutados": 26579,
    "porc_electores_escrutados": 10000,
    "votos_validos": 19123,
    "porc_votos_validos": 7195,
    "votos_positivos": 17890,
    "porc_votos_positivos": 9355,
    "votos_en_blanco": 1021,
    "porc_votos_en_blanco": 534,
    "votos_nulos": 200,
    "porc_votos_nulos": 105,
    "votos_recurridos_impugnados": 12,
    "porc_votos_recurridos_impugnados": 6,
    "cargos_a_elegir": 0,
    "dia": 26,
    "hora": 8,
    "minuto": 15
}