[
    {
        "dia": 26,
        "hora": 1,
        "minuto": 0,
        "codigo_agrupacion": 501,
        "votos_agrupacion": 6777,
        "porc_final_agrupacion": 6561,
        "cargos_electos": 0
    },
    {
        "dia": 26,
        "hora": 1,
        "minuto": 0,
        "codigo_agrupacion": 502,
        "votos_agrupacion": 2000,
        "porc_final_agrupacion": 1936,
        "cargos_electos": 0
    },
    {
        "dia": 26,
        "hora": 1,
        "minuto": 0,
        "codigo_agrupacion": 507,
        "votos_agrupacion": 1389,
        "porc_final_agrupacion": 1345,
        "cargos_electos": 0
    },
    {
        "dia": 26,
        "hora": 1,
        "minuto": 0,
        "codigo_agrupacion": 71,
        "votos_agrupacion": 72,
        "porc_final_agrupacion": 70,
        "cargos_electos": 0
    },
    {
        "dia": 26,
        "hora": 1,
        "minuto": 0,
        "codigo_agrupacion": 189,
        "votos_agrupacion": 47,
        "porc_final_agrupacion": 45,
        "cargos_electos": 0
    },
    {
        "dia": 26,
        "hora": 1,
        "minuto": 0,
        "codigo_agrupacion": 506,
        "votos_agrupacion": 45,
        "porc_final_agrupacion": 44,
        "cargos_electos": 0
    }
]