{
    "mesas_totales": 47,
    "mesas_escrutadas": 47,
    "porc_mesas_escrutadas": 10000,
    "electores": 15226,
    "votantes": 12870,
    "participacion_sobre_censo": 8453,
    "participacion_sobre_escrutado": 8453,
    "electores_escrutados": 15226,
    "porc_electores_escrutados": 10000,
    "votos_validos": 12870,
    "porc_votos_validos": 8453,
    "votos_positivos": 11594,
    "porc_votos_positivos": 9009,
    "votos_en_blanco": 1245,
    "porc_votos_en_blanco": 967,
    "votos_nulos": 25,
    "porc_votos_nulos": 19,
    "votos_recurridos_impugnados": 6,
    "porc_votos_recurridos_impugnados": 5,
    "cargos_a_elegir": 0,
    "dia": 26,
    "hora": 6,
    "minuto": 15
}