{
    "mesas_totales": 48,
    "mesas_escrutadas": 48,
    "porc_mesas_escrutadas": 10000,
    "electores": 15449,
    "votantes": 13108,
    "participacion_sobre_censo": 8485,
    "participacion_sobre_escrutado": 8485,
    "electores_escrutados": 15449,
    "porc_electores_escrutados": 10000,
    "votos_validos": 13108,
    "porc_votos_validos": 8485,
    "votos_positivos": 12232,
    "porc_votos_positivos": 9332,
    "votos_en_blanco": 842,
    "porc_votos_en_blanco": 642,
    "votos_nulos": 26,
    "porc_votos_nulos": 20,
    "votos_recurridos_impugnados": 8,
    "porc_votos_recurridos_impugnados": 6,
    "cargos_a_elegir": 1,
    "dia": 26,
    "hora": 6,
    "minuto": 15
}