{
    "mesas_totales": 51,
    "mesas_escrutadas": 51,
    "porc_mesas_escrutadas": 10000,
    "electores": 16087,
    "votantes": 12025,
    "participacion_sobre_censo": 7475,
    "participacion_sobre_escrutado": 7475,
    "electores_escrutados": 16087,
    "porc_electores_escrutados": 10000,
    "votos_validos": 12025,
    "porc_votos_validos": 7475,
    "votos_positivos": 11828,
    "porc_votos_positivos": 9836,
    "votos_en_blanco": 185,
    "porc_votos_en_blanco": 154,
    "votos_nulos": 10,
    "porc_votos_nulos": 8,
    "votos_recurridos_impugnados": 2,
    "porc_votos_recurridos_impugnados": 2,
    "cargos_a_elegir": 0,
    "dia": 25,
    "hora": 21,
    "minuto": 50
}