[
    {
        "dia": 26,
        "hora": 2,
        "minuto": 55,
        "codigo_agrupacion": 135,
        "votos_agrupacion": 84379,
        "porc_final_agrupacion": 5439,
        "cargos_electos": 0
    },
    {
        "dia": 26,
        "hora": 2,
        "minuto": 55,
        "codigo_agrupacion": 510,
        "votos_agrupacion": 29315,
        "porc_final_agrupacion": 1890,
        "cargos_electos": 0
    },
    {
        "dia": 26,
        "hora": 2,
        "minuto": 55,
        "codigo_agrupacion": 131,
        "votos_agrupacion": 23300,
        "porc_final_agrupacion": 1502,
        "cargos_electos": 0
    },
    {
        "dia": 26,
        "hora": 2,
        "minuto": 55,
        "codigo_agrupacion": 137,
        "votos_agrupacion": 10261,
        "porc_final_agrupacion": 661,
        "cargos_electos": 0
    },
    {
        "dia": 26,
        "hora": 2,
        "minuto": 55,
        "codigo_agrupacion": 132,
        "votos_agrupacion": 4884,
        "porc_final_agrupacion": 315,
        "cargos_electos": 0
    },
    {
        "dia": 26,
        "hora": 2,
        "minuto": 55,
        "codigo_agrupacion": 63,
        "votos_agrupacion": 3002,
        "porc_final_agrupacion": 194,
        "cargos_electos": 0
    }
]