{
    "mesas_totales": 12549,
    "mesas_escrutadas": 12053,
    "porc_mesas_escrutadas": 9605,
    "electores": 4410629,
    "votantes": 3353059,
    "participacion_sobre_censo": 7602,
    "participacion_sobre_escrutado": 7913,
    "electores_escrutados": 4237493,
    "porc_electores_escrutados": 9607,
    "votos_validos": 3353059,
    "porc_votos_validos": 7602,
    "votos_positivos": 3012301,
    "porc_votos_positivos": 8984,
    "votos_en_blanco": 321293,
    "porc_votos_en_blanco": 958,
    "votos_nulos": 17106,
    "porc_votos_nulos": 51,
    "votos_recurridos_impugnados": 2359,
    "porc_votos_recurridos_impugnados": 7,
    "cargos_a_elegir": 9,
    "dia": 26,
    "hora": 9,
    "minuto": 50
}