{
    "mesas_totales": 32,
    "mesas_escrutadas": 31,
    "porc_mesas_escrutadas": 9688,
    "electores": 9780,
    "votantes": 8043,
    "participacion_sobre_censo": 8224,
    "participacion_sobre_escrutado": 8227,
    "electores_escrutados": 9776,
    "porc_electores_escrutados": 9996,
    "votos_validos": 8043,
    "porc_votos_validos": 8224,
    "votos_positivos": 7752,
    "porc_votos_positivos": 9638,
    "votos_en_blanco": 278,
    "porc_votos_en_blanco": 346,
    "votos_nulos": 13,
    "porc_votos_nulos": 16,
    "votos_recurridos_impugnados": 0,
    "porc_votos_recurridos_impugnados": 0,
    "cargos_a_elegir": 0,
    "dia": 26,
    "hora": 0,
    "minuto": 30
}